stringparser.py
stringparser-0.6.dist-info/LICENSE
stringparser-0.6.dist-info/METADATA
stringparser-0.6.dist-info/WHEEL
stringparser-0.6.dist-info/top_level.txt
stringparser-0.6.dist-info/zip-safe
stringparser-0.6.dist-info/RECORD
